README.md
setup.py
envault/__init__.py
envault/aws.py
envault/cli.py
envault/shell.py
envault/vault.py
envault.egg-info/PKG-INFO
envault.egg-info/SOURCES.txt
envault.egg-info/dependency_links.txt
envault.egg-info/entry_points.txt
envault.egg-info/requires.txt
envault.egg-info/top_level.txt
envault/utils/__init__.py
envault/utils/config.py
envault/utils/yaml.py