Metadata-Version: 1.0
Name: envault
Version: 0.4.4
Summary: A simple CLI tool to run processes with secrets from HashiCorp Vault.
Home-page: https://github.com/pratishshr/envault
Author: Pratish Shrestha
Author-email: pratishshr@gmail.com
License: UNKNOWN
Platform: UNKNOWN
